somedecorators/__init__.py
somedecorators/config.py
somedecorators/email.py
somedecorators/ewechat_robot.py
somedecorators/log.py
somedecorators/retry.py
somedecorators/timeit.py
somedecorators/wechat.py
somedecorators/conf/__init__.py
somedecorators/conf/global_settings.py
somedecorators-1.2.6.dist-info/LICENSE
somedecorators-1.2.6.dist-info/METADATA
somedecorators-1.2.6.dist-info/WHEEL
somedecorators-1.2.6.dist-info/top_level.txt
somedecorators-1.2.6.dist-info/RECORD
