Metadata-Version: 2.1
Name: somedecorators
Version: 1.2.6
Summary: Some useful decorators in Python.
Home-page: https://github.com/somenzz/somedecorators
Author: somenzz
Author-email: somenzz@163.com
License: MIT
Keywords: awesome decorators
Classifier: Development Status :: 3 - Alpha
Classifier: Intended Audience :: Developers
Classifier: License :: OSI Approved :: MIT License
Classifier: Operating System :: OS Independent
Classifier: Programming Language :: Python
Classifier: Programming Language :: Python :: 3
Classifier: Topic :: Software Development
Classifier: Topic :: Software Development :: Libraries :: Python Modules
Classifier: Topic :: Utilities
License-File: LICENSE
Requires-Dist: djangomail
Requires-Dist: wechat-enterprise-sdk
Requires-Dist: PyYAML
Requires-Dist: requests
